sneakydog_object_storage_service/__init__.py
sneakydog_object_storage_service-0.1.4.dist-info/METADATA
sneakydog_object_storage_service-0.1.4.dist-info/WHEEL
sneakydog_object_storage_service-0.1.4.dist-info/entry_points.txt
sneakydog_object_storage_service-0.1.4.dist-info/RECORD
