Metadata-Version: 2.4
Name: sneakydog_object_storage_service
Version: 0.1.4
Summary: Sneakydog object storage service
Author-email: "董 福州 (DONG FUZHOU)" <sneakydog@yeah.net>
Requires-Python: >=3.10
Requires-Dist: boto3>=1.42.21
Requires-Dist: minio>=7.2.20
Requires-Dist: mypy-boto3-s3>=1.42.10
Requires-Dist: ruff>=0.14.10
